Workbook

Sheet FRAN 1
B1: PEDIDOS POR BASE | O1: CUBICAJE DE TU PEDIDO POR BASE
A2: CODIGO | B2: DENOMINACION | C2: CANTIDAD | D2: suma | E2: CUBICAJE A LA CARTA | F2: TOTAL PRECIO | G2: IVA | H2: PESO UNITARIO | I2: TOTAL PESO | J2: BASES | K2: FAMILIA DE PRODUCTOS | L2: CUBICAJE | M2: TOTAL | O2: CUBICAJE TOTAL | Q2: PALLET | S2: LINEA DE PRODUCTOS | V2: CANT. | W2: BASES | X2: CUBICAJE | Y2: CANT.X BASE | Z2: cubicaje x base
A3: 4000062 | B3: ANANA A LA CREMA 7,800 KG GRIDO | C3: 1 | D3: =SUM(C3:C40) | E3: =VLOOKUP(A3,MATERIALES!A497:D591,4,0) | F3: =E3*C3 | G3: =F3*1.21 | H3: =VLOOKUP(A3,MATERIALES!$A:$E,5,0) | I3: =C3*H3 | J3: 25 | K3: GRANEL | L3: =VLOOKUP(A3,MATERIALES!$A:$D,4,0) | M3: =L3*C3 | N3: % | O3: =SUM(X3:X13) | Q3: {=_xlfn.IFS(O3<=100,1,O3<=200,2,O3<=300,3,O3<=400,4,O3<=500,5,O3<=600,6,O3<=700,7,O3<=800,8,O3<=900,9,O3<=1000,10,O3<=1100,11,O3<=1200,12,O3<=1300,13,O3<=1400,14,O3<=1500,15,O3<=1600,16,O3<=1700,17,O3<=1800,18,O3<=1900,19,O3<=2000,20,O3<=2100,21,O3<=2200,22,O3<=2300,23,O3<=2400,24,O3<=2500,25,O3<=2600,26,O3<=2700,27,O3<=2800,28)} | R3: =Q3 | S3: GRANEL | V3: =SUMIF($K:$K,S3,$C:$C) | W3: =V3/25 | X3: =SUMIF($K:$K,S3,$M:$M) | Y3: 25 | Z3: 0.2
A4: 4000048 | B4: BANANA C/DULC LECHE 7,800 KG GRIDO | C4: 13 | E4: =VLOOKUP(A4,MATERIALES!A498:D592,4,0) | F4: =E4*C4 | G4: =F4*1.21 | H4: =VLOOKUP(A4,MATERIALES!$A:$E,5,0) | I4: =C4*H4 | K4: GRANEL | L4: =VLOOKUP(A4,MATERIALES!$A:$D,4,0) | M4: =L4*C4 | S4: POTES 3L | V4: =SUMIF($K:$K,S4,$C:$C) | W4: =V4/15 | X4: =SUMIF($K:$K,S4,$M:$M) | Y4: 15 | Z4: 0.1635
A5: 4000608 | B5: CANDY 7,800 KG GRIDO | C5: 0 | E5: =VLOOKUP(A5,MATERIALES!A499:D593,4,0) | F5: =E5*C5 | G5: =F5*1.21 | H5: =VLOOKUP(A5,MATERIALES!$A:$E,5,0) | I5: =C5*H5 | K5: GRANEL | L5: =VLOOKUP(A5,MATERIALES!$A:$D,4,0) | M5: =L5*C5 | O5: KILOS | S5: TORTAS | V5: =SUMIF($K:$K,S5,$C:$C) | W5: =V5/10 | X5: =SUMIF($K:$K,S5,$M:$M) | Y5: 10 | Z5: 0.12
A6: 4000193 | B6: CAPPUCCINO GRANIZADO 7,800 KG GRIDO | C6: 2 | E6: =VLOOKUP(A6,MATERIALES!A500:D594,4,0) | F6: =E6*C6 | G6: =F6*1.21 | H6: =VLOOKUP(A6,MATERIALES!$A:$E,5,0) | I6: =C6*H6 | K6: GRANEL | L6: =VLOOKUP(A6,MATERIALES!$A:$D,4,0) | M6: =L6*C6 | O6: =SUM(I3:I113) | S6: TENTACION | V6: =SUMIF($K:$K,S6,$C:$C) | W6: =V6/15 | X6: =SUMIF($K:$K,S6,$M:$M) | Y6: 15 | Z6: 0.0765
A7: 4000070 | B7: CEREZA 7,800 KG - GRIDO | C7: 6 | E7: =VLOOKUP(A7,MATERIALES!A501:D595,4,0) | F7: =E7*C7 | G7: =F7*1.21 | H7: =VLOOKUP(A7,MATERIALES!$A:$E,5,0) | I7: =C7*H7 | K7: GRANEL | L7: =VLOOKUP(A7,MATERIALES!$A:$D,4,0) | M7: =L7*C7 | S7: PALITOS | V7: =SUMIF($K:$K,S7,$C:$C) | W7: =V7/15 | X7: =SUMIF($K:$K,S7,$M:$M) | Y7: 15 | Z7: 0.123
A8: 4000827 | B8: CHOCO BLANCO OREO 7,800 KG GRIDO | C8: 6 | E8: =VLOOKUP(A8,MATERIALES!A502:D596,4,0) | F8: =E8*C8 | G8: =F8*1.21 | H8: =VLOOKUP(A8,MATERIALES!$A:$E,5,0) | I8: =C8*H8 | K8: GRANEL | L8: =VLOOKUP(A8,MATERIALES!$A:$D,4,0) | M8: =L8*C8 | O8: CUBICAJE A LA CARTA | Q8: PALLET | S8: PALITOS NUEVOS X 10 UNID | V8: =SUMIF($K:$K,S8,$C:$C) | W8: =V8/12 | X8: =SUMIF($K:$K,S8,$M:$M) | Y8: 12 | Z8: 0.1666
A9: 4000043 | B9: CHOCOLATE 7,800 KG GRIDO | C9: 22 | E9: =VLOOKUP(A9,MATERIALES!A503:D597,4,0) | F9: =E9*C9 | G9: =F9*1.21 | H9: =VLOOKUP(A9,MATERIALES!$A:$E,5,0) | I9: =C9*H9 | K9: GRANEL | L9: =VLOOKUP(A9,MATERIALES!$A:$D,4,0) | M9: =L9*C9 | N9: % | O9: =SUM(F3:F130) | Q9: {=_xlfn.IFS(O9<=100,1,O9<=200,2,O9<=300,3,O9<=400,4,O9<=500,5,O9<=600,6,O9<=700,7,O9<=800,8,O9<=900,9,O9<=1000,10,O9<=1100,11,O9<=1200,12,O9<=1300,13,O9<=1400,14,O9<=1500,15,O9<=1600,16,O9<=1700,17,O9<=1800,18,O9<=1900,19,O9<=2000,20,O9<=2100,21,O9<=2200,22,O9<=2300,23,O9<=2400,24,O9<=2500,25,O9<=2600,26,O9<=2700,27,O9<=2800,28)} | S9: ESCOCES-SHOT-SECRETO | V9: =SUMIF($K:$K,S9,$C:$C) | W9: =V9/10 | X9: =SUMIF($K:$K,S9,$M:$M) | Y9: 10 | Z9: 0.077
A10: 4000059 | B10: CHOCOLATE BLANCO 7,800 KG GRIDO | C10: 3 | E10: =VLOOKUP(A10,MATERIALES!A504:D598,4,0) | F10: =E10*C10 | G10: =F10*1.21 | H10: =VLOOKUP(A10,MATERIALES!$A:$E,5,0) | I10: =C10*H10 | K10: GRANEL | L10: =VLOOKUP(A10,MATERIALES!$A:$D,4,0) | M10: =L10*C10 | S10: PORCION | V10: =SUMIF($K:$K,S10,$C:$C) | W10: =V10/10 | X10: =SUMIF($K:$K,S10,$M:$M) | Y10: 10 | Z10: 0.077
A11: 4000067 | B11: CHOCOLATE C/ALMEN 7,800 KG GRIDO | C11: 13 | E11: =VLOOKUP(A11,MATERIALES!A505:D599,4,0) | F11: =E11*C11 | G11: =F11*1.21 | H11: =VLOOKUP(A11,MATERIALES!$A:$E,5,0) | I11: =C11*H11 | K11: GRANEL | L11: =VLOOKUP(A11,MATERIALES!$A:$D,4,0) | M11: =L11*C11 | S11: BARRAS | V11: =SUMIF($K:$K,S11,$C:$C) | W11: =V11/12 | X11: =SUMIF($K:$K,S11,$M:$M) | Y11: 12 | Z11: 0.0696
A12: 4000061 | B12: CHOCOLATE MANI CRUNCH 7,800 KG GRIDO | C12: 0 | E12: =VLOOKUP(A12,MATERIALES!A506:D600,4,0) | F12: =E12*C12 | G12: =F12*1.21 | H12: =VLOOKUP(A12,MATERIALES!$A:$E,5,0) | I12: =C12*H12 | K12: GRANEL | L12: =VLOOKUP(A12,MATERIALES!$A:$D,4,0) | M12: =L12*C12 | S12: ALIM.CONGELADOS CAJAS GRANDES | T12: =SUMIF(#REF!,"C",C83:C113) | U12: 16.668 | V12: =SUMIF($K:$K,S12,$C:$C) | W12: =V12/5 | X12: =SUMIF($K:$K,S12,$M:$M) | Y12: 5 | Z12: 0.06
A13: 4000057 | B13: CHOCOLATE SUIZO 7,800 KG GRIDO | C13: 3 | E13: =VLOOKUP(A13,MATERIALES!A507:D601,4,0) | F13: =E13*C13 | G13: =F13*1.21 | H13: =VLOOKUP(A13,MATERIALES!$A:$E,5,0) | I13: =C13*H13 | K13: GRANEL | L13: =VLOOKUP(A13,MATERIALES!$A:$D,4,0) | M13: =L13*C13 | N13: COMPARATIVO CON RESPECTO AL CUBICAJE DE PEDIDOS A LA CARTA | S13: ALIM.CONGELADOS CAJAS CHICAS | V13: =SUMIF($K:$K,S13,$C:$C) | W13: =V13/5 | X13: =SUMIF($K:$K,S13,$M:$M) | Y13: 5 | Z13: 0.03
A14: 4000045 | B14: CREMA AMERICANA 7,800 KG GRIDO | C14: 17 | E14: =VLOOKUP(A14,MATERIALES!A508:D602,4,0) | F14: =E14*C14 | G14: =F14*1.21 | H14: =VLOOKUP(A14,MATERIALES!$A:$E,5,0) | I14: =C14*H14 | K14: GRANEL | L14: =VLOOKUP(A14,MATERIALES!$A:$D,4,0) | M14: =L14*C14 | S14: BULTOS | V14: =SUM(V3:V13) | W14: =O3 | X14: =110-W14 | AA14: =$O$3 | AB14: =IF(AA14<100,0,O3) | AD14: =IF(AB14<100,0,101) | AE14: =Z15-AA14 | AF14: =100-AE14 | AG14: =AE14
A15: 4000051 | B15: CREMA COOKIE 7,800 KG GRIDO | C15: 9 | E15: =VLOOKUP(A15,MATERIALES!A509:D603,4,0) | F15: =E15*C15 | G15: =F15*1.21 | H15: =VLOOKUP(A15,MATERIALES!$A:$E,5,0) | I15: =C15*H15 | K15: GRANEL | L15: =VLOOKUP(A15,MATERIALES!$A:$D,4,0) | M15: =L15*C15 | Z15: 200 | AA15: =$O$3 | AB15: =IF(AA15<200,0,$O$3) | AD15: =IF(AB15<100,0,101) | AE15: =Z16-AA15 | AF15: =100-AE15 | AG15: =AE15
A16: 4000066 | B16: CREMA RUSA 7,800 KG GRIDO | C16: 2 | E16: =VLOOKUP(A16,MATERIALES!A510:D604,4,0) | F16: =E16*C16 | G16: =F16*1.21 | H16: =VLOOKUP(A16,MATERIALES!$A:$E,5,0) | I16: =C16*H16 | K16: GRANEL | L16: =VLOOKUP(A16,MATERIALES!$A:$D,4,0) | M16: =L16*C16 | O16: DIFERENCIA ENTRE MODALIDADES | S16: BASES | V16: =SUM(W3:W12) | Z16: 300 | AA16: =$O$3 | AB16: =IF(AA16<300,0,$O$3) | AD16: =IF(AB16<100,0,101) | AE16: =Z17-AA16 | AF16: =100-AE16 | AG16: =AE16
A17: 4000041 | B17: DULCE DE LECHE 7,800 KG GRIDO | C17: 21 | E17: =VLOOKUP(A17,MATERIALES!A511:D605,4,0) | F17: =E17*C17 | G17: =F17*1.21 | H17: =VLOOKUP(A17,MATERIALES!$A:$E,5,0) | I17: =C17*H17 | K17: GRANEL | L17: =VLOOKUP(A17,MATERIALES!$A:$D,4,0) | M17: =L17*C17 | N17: % | O17: =O9-O3 | Z17: 400 | AA17: =$O$3 | AB17: =IF(AA17<400,0,$O$3) | AD17: =IF(AB17<100,0,101) | AE17: =Z18-AA17 | AF17: =100-AE17 | AG17: =AE17
A18: 4000069 | B18: DULCE LECHE C/BROWNIE 7,800 KG GRIDO | C18: 0 | E18: =VLOOKUP(A18,MATERIALES!A512:D606,4,0) | F18: =E18*C18 | G18: =F18*1.21 | H18: =VLOOKUP(A18,MATERIALES!$A:$E,5,0) | I18: =C18*H18 | K18: GRANEL | L18: =VLOOKUP(A18,MATERIALES!$A:$D,4,0) | M18: =L18*C18 | Z18: 500 | AA18: =$O$3 | AB18: =IF(AA18<400,0,$O$3) | AD18: =IF(AB18<100,0,101) | AE18: =Z19-AA18 | AF18: =100-AE18 | AG18: =AE18
A19: 4000068 | B19: DULCE LECHE C/NUEZ 7,800 KG GRIDO | C19: 1 | E19: =VLOOKUP(A19,MATERIALES!A513:D607,4,0) | F19: =E19*C19 | G19: =F19*1.21 | H19: =VLOOKUP(A19,MATERIALES!$A:$E,5,0) | I19: =C19*H19 | K19: GRANEL | L19: =VLOOKUP(A19,MATERIALES!$A:$D,4,0) | M19: =L19*C19 | Z19: 600 | AA19: =$O$3 | AB19: =IF(AA19<400,0,$O$3) | AD19: =IF(AB19<100,0,101) | AE19: =Z20-AA19 | AF19: =100-AE19 | AG19: =AE19
A20: 4000046 | B20: DULCE LECHE GRANIZADO 7,800 KG GRIDO | C20: 22 | E20: =VLOOKUP(A20,MATERIALES!A514:D608,4,0) | F20: =E20*C20 | G20: =F20*1.21 | H20: =VLOOKUP(A20,MATERIALES!$A:$E,5,0) | I20: =C20*H20 | K20: GRANEL | L20: =VLOOKUP(A20,MATERIALES!$A:$D,4,0) | M20: =L20*C20 | Z20: 700 | AA20: =$O$3 | AB20: =IF(AA20<400,0,$O$3) | AD20: =IF(AB20<100,0,101) | AE20: =Z21-AA20 | AF20: =100-AE20 | AG20: =AE20
A21: 4000316 | B21: DURAZNO A LA CREMA 7,800 KG GRIDO | C21: 0 | E21: =VLOOKUP(A21,MATERIALES!A515:D609,4,0) | F21: =E21*C21 | G21: =F21*1.21 | H21: =VLOOKUP(A21,MATERIALES!$A:$E,5,0) | I21: =C21*H21 | K21: GRANEL | L21: =VLOOKUP(A21,MATERIALES!$A:$D,4,0) | M21: =L21*C21 | Z21: 800 | AA21: =$O$3 | AB21: =IF(AA21<400,0,$O$3) | AD21: =IF(AB21<100,0,101) | AE21: =Z22-AA21 | AF21: =100-AE21 | AG21: =AE21
A22: 4000047 | B22: FLAN 7,800 KG GRIDO | C22: 4 | E22: =VLOOKUP(A22,MATERIALES!A516:D610,4,0) | F22: =E22*C22 | G22: =F22*1.21 | H22: =VLOOKUP(A22,MATERIALES!$A:$E,5,0) | I22: =C22*H22 | K22: GRANEL | L22: =VLOOKUP(A22,MATERIALES!$A:$D,4,0) | M22: =L22*C22 | Z22: 900 | AA22: =$O$3 | AB22: =IF(AA22<400,0,$O$3) | AD22: =IF(AB22<100,0,101) | AE22: =Z23-AA22 | AF22: =100-AE22 | AG22: =AE22
A23: 4000042 | B23: FRUTILLA A LA CREMA 7,800KG GRIDO | C23: 22 | E23: =VLOOKUP(A23,MATERIALES!A517:D611,4,0) | F23: =E23*C23 | G23: =F23*1.21 | H23: =VLOOKUP(A23,MATERIALES!$A:$E,5,0) | I23: =C23*H23 | K23: GRANEL | L23: =VLOOKUP(A23,MATERIALES!$A:$D,4,0) | M23: =L23*C23 | Z23: 1000 | AA23: =$O$3 | AB23: =IF(AA23<400,0,$O$3) | AD23: =IF(AB23<100,0,101) | AE23: =Z24-AA23 | AF23: =100-AE23 | AG23: =AE23
A24: 4000194 | B24: FRUTILLA AL AGUA 7,800 KG GRIDO | C24: 0 | E24: =VLOOKUP(A24,MATERIALES!A518:D612,4,0) | F24: =E24*C24 | G24: =F24*1.21 | H24: =VLOOKUP(A24,MATERIALES!$A:$E,5,0) | I24: =C24*H24 | K24: GRANEL | L24: =VLOOKUP(A24,MATERIALES!$A:$D,4,0) | M24: =L24*C24 | Z24: 1100 | AA24: =$O$3 | AB24: =IF(AA24<400,0,$O$3) | AD24: =IF(AB24<100,0,101) | AE24: =Z25-AA24 | AF24: =100-AE24 | AG24: =AE24
A25: 4000607 | B25: FRUTOS ROJOS AL AGUA 7,800 KG GRIDO | C25: 2 | E25: =VLOOKUP(A25,MATERIALES!A519:D613,4,0) | F25: =E25*C25 | G25: =F25*1.21 | H25: =VLOOKUP(A25,MATERIALES!$A:$E,5,0) | I25: =C25*H25 | K25: GRANEL | L25: =VLOOKUP(A25,MATERIALES!$A:$D,4,0) | M25: =L25*C25 | Z25: 1200 | AA25: =$O$3 | AB25: =IF(AA25<400,0,$O$3) | AD25: =IF(AB25<100,0,101) | AE25: =Z26-AA25 | AF25: =100-AE25 | AG25: =AE25
A26: 4000040 | B26: GRANIZADO 7,800 KG GRIDO | C26: 11 | E26: =VLOOKUP(A26,MATERIALES!A520:D614,4,0) | F26: =E26*C26 | G26: =F26*1.21 | H26: =VLOOKUP(A26,MATERIALES!$A:$E,5,0) | I26: =C26*H26 | K26: GRANEL | L26: =VLOOKUP(A26,MATERIALES!$A:$D,4,0) | M26: =L26*C26 | Z26: 1300 | AA26: =$O$3 | AB26: =IF(AA26<400,0,$O$3) | AD26: =IF(AB26<100,0,101) | AE26: =Z27-AA26 | AF26: =100-AE26 | AG26: =AE26
A27: 4000056 | B27: KINOTOS AL WHISKY 7,800 KG GRIDO | C27: 0 | E27: =VLOOKUP(A27,MATERIALES!A521:D615,4,0) | F27: =E27*C27 | G27: =F27*1.21 | H27: =VLOOKUP(A27,MATERIALES!$A:$E,5,0) | I27: =C27*H27 | K27: GRANEL | L27: =VLOOKUP(A27,MATERIALES!$A:$D,4,0) | M27: =L27*C27 | Z27: 1400 | AA27: =$O$3 | AB27: =IF(AA27<400,0,$O$3) | AD27: =IF(AB27<100,0,101) | AE27: =Z28-AA27 | AF27: =100-AE27 | AG27: =AE27
A28: 4000036 | B28: LIMON AL AGUA 7,800 KG GRIDO | C28: 5 | E28: =VLOOKUP(A28,MATERIALES!A522:D616,4,0) | F28: =E28*C28 | G28: =F28*1.21 | H28: =VLOOKUP(A28,MATERIALES!$A:$E,5,0) | I28: =C28*H28 | K28: GRANEL | L28: =VLOOKUP(A28,MATERIALES!$A:$D,4,0) | M28: =L28*C28 | Z28: 1500 | AA28: =$O$3 | AB28: =IF(AA28<400,0,$O$3) | AD28: =IF(AB28<100,0,101) | AE28: =Z29-AA28 | AF28: =100-AE28 | AG28: =AE28
A29: 4000038 | B29: MARACUYA AL AGUA 7,800 KG GRIDO | C29: 3 | E29: =VLOOKUP(A29,MATERIALES!A523:D617,4,0) | F29: =E29*C29 | G29: =F29*1.21 | H29: =VLOOKUP(A29,MATERIALES!$A:$E,5,0) | I29: =C29*H29 | K29: GRANEL | L29: =VLOOKUP(A29,MATERIALES!$A:$D,4,0) | M29: =L29*C29 | Z29: 1600 | AA29: =$O$3 | AB29: =IF(AA29<400,0,$O$3) | AD29: =IF(AB29<100,0,101) | AE29: =Z30-AA29 | AF29: =100-AE29 | AG29: =AE29
... A32: 4000049 | B32: MENTA GRANIZADA 7,800 KG GRIDO | C32: 9 | E32: =VLOOKUP(A32,MATERIALES!A526:D620,4,0) | F32: =E32*C32 | G32: =F32*1.21 | H32: =VLOOKUP(A32,MATERIALES!$A:$E,5,0) | I32: =C32*H32 | K32: GRANEL | L32: =VLOOKUP(A32,MATERIALES!$A:$D,4,0) | M32: =L32*C32 | Z32: 1900 | AA32: =$O$3 | AB32: =IF(AA32<400,0,$O$3) | AD32: =IF(AB32<100,0,101) | AE32: =Z33-AA32 | AF32: =100-AE32 | AG32: =AE32
A33: 4000039 | B33: NARANJA AL AGUA 12 7,800 KG GRIDO | C33: 1 | E33: =VLOOKUP(A33,MATERIALES!A527:D621,4,0) | F33: =E33*C33 | G33: =F33*1.21 | H33: =VLOOKUP(A33,MATERIALES!$A:$E,5,0) | I33: =C33*H33 | K33: GRANEL | L33: =VLOOKUP(A33,MATERIALES!$A:$D,4,0) | M33: =L33*C33 | Z33: 2000
A34: 4000754 | B34: PISTACHO 7,800 KG GRIDO | C34: 0 | E34: =VLOOKUP(A34,MATERIALES!A528:D622,4,0) | F34: =E34*C34 | G34: =F34*1.21 | H34: =VLOOKUP(A34,MATERIALES!$A:$E,5,0) | I34: =C34*H34 | K34: GRANEL | L34: =VLOOKUP(A34,MATERIALES!$A:$D,4,0) | M34: =L34*C34 | AA34: =$O$3 | AB34: =IF(AA34<400,0,$O$3) | AD34: =IF(AB34<100,0,101) | AE34: =Z35-AA34 | AF34: =100-AE34 | AG34: =AE34
A35: 4000065 | B35: SAMBAYON 7,800 KG GRIDO | C35: 0 | E35: =VLOOKUP(A35,MATERIALES!A529:D623,4,0) | F35: =E35*C35 | G35: =F35*1.21 | H35: =VLOOKUP(A35,MATERIALES!$A:$E,5,0) | I35: =C35*H35 | K35: GRANEL | L35: =VLOOKUP(A35,MATERIALES!$A:$D,4,0) | M35: =L35*C35 | Z35: 2100 | AA35: =$O$3 | AB35: =IF(AA35<400,0,$O$3) | AD35: =IF(AB35<100,0,101) | AE35: =Z36-AA35 | AF35: =100-AE35 | AG35: =AE35
A36: 4000064 | B36: SUPER DULCE DE LECHE 7,800 KG GRIDO | C36: 7 | E36: =VLOOKUP(A36,MATERIALES!A530:D624,4,0) | F36: =E36*C36 | G36: =F36*1.21 | H36: =VLOOKUP(A36,MATERIALES!$A:$E,5,0) | I36: =C36*H36 | K36: GRANEL | L36: =VLOOKUP(A36,MATERIALES!$A:$D,4,0) | M36: =L36*C36 | Z36: 2200 | AA36: =$O$3 | AB36: =IF(AA36<400,0,$O$3) | AD36: =IF(AB36<100,0,101) | AE36: =Z37-AA36 | AF36: =100-AE36 | AG36: =AE36
A37: 4000050 | B37: SUPER GRIDITO 7,800 KG GRIDO | C37: 4 | E37: =VLOOKUP(A37,MATERIALES!A531:D625,4,0) | F37: =E37*C37 | G37: =F37*1.21 | H37: =VLOOKUP(A37,MATERIALES!$A:$E,5,0) | I37: =C37*H37 | K37: GRANEL | L37: =VLOOKUP(A37,MATERIALES!$A:$D,4,0) | M37: =L37*C37 | Z37: 2300 | AA37: =$O$3 | AB37: =IF(AA37<400,0,$O$3) | AD37: =IF(AB37<100,0,101) | AE37: =Z38-AA37 | AF37: =100-AE37 | AG37: =AE37
A38: 4000071 | B38: TIRAMISU 7,800 KG GRIDO | C38: 0 | E38: =VLOOKUP(A38,MATERIALES!A532:D626,4,0) | F38: =E38*C38 | G38: =F38*1.21 | H38: =VLOOKUP(A38,MATERIALES!$A:$E,5,0) | I38: =C38*H38 | K38: GRANEL | L38: =VLOOKUP(A38,MATERIALES!$A:$D,4,0) | M38: =L38*C38 | Z38: 2400 | AA38: =$O$3 | AB38: =IF(AA38<400,0,$O$3) | AD38: =IF(AB38<100,0,101) | AE38: =Z39-AA38 | AF38: =100-AE38 | AG38: =AE38
A39: 4000055 | B39: TRAMONTANA 7,800 KG GRIDO | C39: 14 | E39: =VLOOKUP(A39,MATERIALES!A533:D627,4,0) | F39: =E39*C39 | G39: =F39*1.21 | H39: =VLOOKUP(A39,MATERIALES!$A:$E,5,0) | I39: =C39*H39 | K39: GRANEL | L39: =VLOOKUP(A39,MATERIALES!$A:$D,4,0) | M39: =L39*C39 | Z39: 2500 | AA39: =$O$3 | AB39: =IF(AA39<400,0,$O$3) | AD39: =IF(AB39<100,0,101) | AE39: =Z40-AA39 | AF39: =100-AE39 | AG39: =AE39
A40: 4000044 | B40: VAINILLA 7,800 KG GRIDO | C40: 10 | E40: 0.85 | F40: =E40*C40 | G40: =F40*1.21 | H40: =VLOOKUP(A40,MATERIALES!$A:$E,5,0) | I40: =C40*H40 | K40: GRANEL | L40: =VLOOKUP(A40,MATERIALES!$A:$D,4,0) | M40: =L40*C40 | Z40: 2600 | AA40: =$O$3 | AB40: =IF(AA40<400,0,$O$3) | AD40: =IF(AB40<100,0,101) | AE40: =Z41-AA40 | AF40: =100-AE40 | AG40: =AE40
A41: 4000163 | B41: PACK X6 GRIDO FAMILIAR X3LTS NRO 1 GRIDO | C41: 7 | D41: =SUM(C41:C44) | E41: =VLOOKUP(A41,MATERIALES!A535:D629,4,0) | F41: =E41*C41 | G41: =F41*1.21 | H41: =VLOOKUP(A41,MATERIALES!$A:$E,5,0) | I41: =C41*H41 | J41: 15 | K41: POTES 3L | L41: =VLOOKUP(A41,MATERIALES!$A:$D,4,0) | M41: =L41*C41 | Z41: 2700 | AA41: =$O$3 | AB41: =IF(AA41<400,0,$O$3) | AD41: =IF(AB41<100,0,101) | AE41: =Z42-AA41 | AF41: =100-AE41 | AG41: =AE41
A42: 4000164 | B42: PACK X 6 GRIDO FAMILIAR X3 LTS N2 GRIDO | C42: 12 | E42: =VLOOKUP(A42,MATERIALES!A536:D630,4,0) | F42: =E42*C42 | G42: =F42*1.21 | H42: =VLOOKUP(A42,MATERIALES!$A:$E,5,0) | I42: =C42*H42 | K42: POTES 3L | L42: =VLOOKUP(A42,MATERIALES!$A:$D,4,0) | M42: =L42*C42 | Z42: 2800
A43: 4000165 | B43: PACK X6 GRIDO FAMILIAR X 3LTS NRO3 GRIDO | C43: 7 | E43: =VLOOKUP(A43,MATERIALES!A537:D631,4,0) | F43: =E43*C43 | G43: =F43*1.21 | H43: =VLOOKUP(A43,MATERIALES!$A:$E,5,0) | I43: =C43*H43 | K43: POTES 3L | L43: =VLOOKUP(A43,MATERIALES!$A:$D,4,0) | M43: =L43*C43
A44: 4000166 | B44: PACKX 6 GRIDO FAMILIAR X3 LTS N4 GRIDO | C44: 10 | E44: =VLOOKUP(A44,MATERIALES!A538:D632,4,0) | F44: =E44*C44 | G44: =F44*1.21 | H44: =VLOOKUP(A44,MATERIALES!$A:$E,5,0) | I44: =C44*H44 | K44: POTES 3L | L44: =VLOOKUP(A44,MATERIALES!$A:$D,4,0) | M44: =L44*C44
A45: 4000835 | B45: PACK X 6 TORTA COOKIES AND CREAM GR | C45: 12 | D45: =SUM(C45:C48) | E45: =VLOOKUP(A45,MATERIALES!A539:D633,4,0) | F45: =E45*C45 | G45: =F45*1.21 | H45: =VLOOKUP(A45,MATERIALES!$A:$E,5,0) | I45: =C45*H45 | J45: 10 | K45: TORTAS | L45: =VLOOKUP(A45,MATERIALES!$A:$D,4,0) | M45: =L45*C45
A46: 4000446 | B46: PACK x 6 TORTA GRIDO C/RELLENO | C46: 13 | E46: =VLOOKUP(A46,MATERIALES!A540:D634,4,0) | F46: =E46*C46 | G46: =F46*1.21 | H46: =VLOOKUP(A46,MATERIALES!$A:$E,5,0) | I46: =C46*H46 | K46: TORTAS | L46: =VLOOKUP(A46,MATERIALES!$A:$D,4,0) | M46: =L46*C46
A47: 4000892 | B47: PACK X 6 TORTA FRUTILLA GR | C47: 11 | E47: 1.25 | F47: =E47*C47 | H47: 6.27 | K47: TORTAS | L47: 1.2 | M47: =L47*C47
A48: 4000843 | B48: PACK X 6 TORTA COOKIES MOUSSE GR | C48: 0 | E48: =VLOOKUP(A48,MATERIALES!A541:D635,4,0) | F48: =E48*C48 | G48: =F48*1.21 | H48: =VLOOKUP(A48,MATERIALES!$A:$E,5,0) | I48: =C48*H48 | K48: TORTAS | L48: =VLOOKUP(A48,MATERIALES!$A:$D,4,0) | M48: =L48*C48
A49: 4000152 | B49: PACK X 6 POTE X 1LT GRANIZADO GRIDO | C49: 9 | D49: =SUM(C49:C60) | E49: =VLOOKUP(A49,MATERIALES!A542:D636,4,0) | F49: =E49*C49 | G49: =F49*1.21 | H49: =VLOOKUP(A49,MATERIALES!$A:$E,5,0) | I49: =C49*H49 | J49: 15 | K49: TENTACION | L49: 0.51 | M49: =L49*C49
A50: 4000153 | B50: PACKX6 POTE X 1LT D.LECHE GRANIZ GRIDO | C50: 12 | E50: =VLOOKUP(A50,MATERIALES!A543:D637,4,0) | F50: =E50*C50 | G50: =F50*1.21 | H50: =VLOOKUP(A50,MATERIALES!$A:$E,5,0) | I50: =C50*H50 | K50: TENTACION | L50: 0.51 | M50: =L50*C50
A51: 4000155 | B51: PACKX 6 POTE X1LT CHOC C/ALMENDRAS GRIDO | C51: 6 | E51: =VLOOKUP(A51,MATERIALES!A544:D638,4,0) | F51: =E51*C51 | G51: =F51*1.21 | H51: =VLOOKUP(A51,MATERIALES!$A:$E,5,0) | I51: =C51*H51 | K51: TENTACION | L51: 0.51 | M51: =L51*C51
A52: 4000156 | B52: PACK X 6 POTE X 1 LT NRO 6 LIMON - GRIDO | C52: 0 | E52: =VLOOKUP(A52,MATERIALES!A545:D639,4,0) | F52: =E52*C52 | G52: =F52*1.21 | H52: =VLOOKUP(A52,MATERIALES!$A:$E,5,0) | I52: =C52*H52 | K52: TENTACION | L52: 0.51 | M52: =L52*C52
A53: 4000157 | B53: PACK X 6 POTE X 1LT CREMA COOKIE - GRIDO | C53: 5 | E53: =VLOOKUP(A53,MATERIALES!A546:D640,4,0) | F53: =E53*C53 | G53: =F53*1.21 | H53: =VLOOKUP(A53,MATERIALES!$A:$E,5,0) | I53: =C53*H53 | K53: TENTACION | L53: 0.51 | M53: =L53*C53
A54: 4000158 | B54: PACK X 6 POTE X 1 LT CHOCOLATE GRIDO | C54: 5 | E54: =VLOOKUP(A54,MATERIALES!A547:D641,4,0) | F54: =E54*C54 | G54: =F54*1.21 | H54: =VLOOKUP(A54,MATERIALES!$A:$E,5,0) | I54: =C54*H54 | K54: TENTACION | L54: 0.51 | M54: =L54*C54
A55: 4000159 | B55: PACK X 6 POTE X 1 LT NRO 9 DDL - GRIDO | C55: 6 | E55: =VLOOKUP(A55,MATERIALES!A548:D642,4,0) | F55: =E55*C55 | G55: =F55*1.21 | H55: =VLOOKUP(A55,MATERIALES!$A:$E,5,0) | I55: =C55*H55 | K55: TENTACION | L55: 0.51 | M55: =L55*C55
A56: 4000160 | B56: PACK X 6 POTE X 1 LT FRUTILLA - GRIDO | C56: 5 | E56: =VLOOKUP(A56,MATERIALES!A549:D643,4,0) | F56: =E56*C56 | G56: =F56*1.21 | H56: =VLOOKUP(A56,MATERIALES!$A:$E,5,0) | I56: =C56*H56 | K56: TENTACION | L56: 0.51 | M56: =L56*C56
A57: 4000161 | B57: PACK X 6 POTE X 1 LT VAINILLA - GRIDO | C57: 5 | E57: =VLOOKUP(A57,MATERIALES!A550:D644,4,0) | F57: =E57*C57 | G57: =F57*1.21 | H57: =VLOOKUP(A57,MATERIALES!$A:$E,5,0) | I57: =C57*H57 | K57: TENTACION | L57: 0.51 | M57: =L57*C57
A58: 4000162 | B58: PACK X6 POTE X 1LT CREMA AMERICANA GRIDO | C58: 6 | E58: =VLOOKUP(A58,MATERIALES!A551:D645,4,0) | F58: =E58*C58 | G58: =F58*1.21 | H58: =VLOOKUP(A58,MATERIALES!$A:$E,5,0) | I58: =C58*H58 | K58: TENTACION | L58: 0.51 | M58: =L58*C58
A59: 4000341 | B59: PACK 6 POTES X 1 LT GALLETITA TODDY -GRI | C59: 6 | E59: =VLOOKUP(A59,MATERIALES!A552:D646,4,0) | F59: =E59*C59 | G59: =F59*1.21 | H59: =VLOOKUP(A59,MATERIALES!$A:$E,5,0) | I59: =C59*H59 | K59: TENTACION | L59: 0.51 | M59: =L59*C59
A60: 4000670 | B60: PACK X 6 POTE X 1 LT MENTA GRANIZ. GRIDO | C60: 6 | E60: =VLOOKUP(A60,MATERIALES!A555:D649,4,0) | F60: =E60*C60 | G60: =F60*1.21 | H60: =VLOOKUP(A60,MATERIALES!$A:$E,5,0) | I60: =C60*H60 | K60: TENTACION | L60: 0.51 | M60: =L60*C60
A61: 4000136 | B61: PACK 4 CAJGRIDO CREM DE CREMA AMERICANA | C61: 16 | D61: =SUM(C61:C66) | E61: =VLOOKUP(A61,MATERIALES!A556:D650,4,0) | F61: =E61*C61 | G61: =F61*1.21 | H61: =VLOOKUP(A61,MATERIALES!$A:$E,5,0) | I61: =C61*H61 | J61: 15 | K61: PALITOS | L61: =VLOOKUP(A61,MATERIALES!$A:$D,4,0) | M61: =L61*C61
A62: 4000137 | B62: PACK 4 CAJAS GRIDO CREMOSO DE FRUTILLA | C62: 16 | E62: =VLOOKUP(A62,MATERIALES!A557:D651,4,0) | F62: =E62*C62 | G62: =F62*1.21 | H62: =VLOOKUP(A62,MATERIALES!$A:$E,5,0) | I62: =C62*H62 | K62: PALITOS | L62: =VLOOKUP(A62,MATERIALES!$A:$D,4,0) | M62: =L62*C62
A63: 4000138 | B63: PACK 4 CAJAS GRIDO FRUTAL FRUTILLA X20 | C63: 41 | E63: =VLOOKUP(A63,MATERIALES!A558:D652,4,0) | F63: =E63*C63 | G63: =F63*1.21 | H63: =VLOOKUP(A63,MATERIALES!$A:$E,5,0) | I63: =C63*H63 | K63: PALITOS | L63: =VLOOKUP(A63,MATERIALES!$A:$D,4,0) | M63: =L63*C63
A64: 4000139 | B64: PACK 4 CAJAS GRIDO FRUTAL LIMON X20 | C64: 29 | E64: =VLOOKUP(A64,MATERIALES!A559:D653,4,0) | F64: =E64*C64 | G64: =F64*1.21 | H64: =VLOOKUP(A64,MATERIALES!$A:$E,5,0) | I64: =C64*H64 | K64: PALITOS | L64: =VLOOKUP(A64,MATERIALES!$A:$D,4,0) | M64: =L64*C64
A65: 4000140 | B65: PACK 4 CAJAS PALITO BOMBON X20 - GRIDO | C65: 64 | E65: =VLOOKUP(A65,MATERIALES!A560:D654,4,0) | F65: =E65*C65 | G65: =F65*1.21 | H65: =VLOOKUP(A65,MATERIALES!$A:$E,5,0) | I65: =C65*H65 | K65: PALITOS | L65: =VLOOKUP(A65,MATERIALES!$A:$D,4,0) | M65: =L65*C65
A66: 4000141 | B66: PACK 4 CAJAS GRIDO FRUTAL NARANJA X20 | C66: 22 | E66: =VLOOKUP(A66,MATERIALES!A561:D655,4,0) | F66: =E66*C66 | G66: =F66*1.21 | H66: =VLOOKUP(A66,MATERIALES!$A:$E,5,0) | I66: =C66*H66 | K66: PALITOS | L66: =VLOOKUP(A66,MATERIALES!$A:$D,4,0) | M66: =L66*C66
A67: 4000856 | B67: PACK 10 CAJ. GRIDO FRUTAL FRUTILLA X 10 | C67: 0 | D67: =SUM(C67:C71) | E67: 1.388 | F67: =E67*C67 | J67: 12 | K67: PALITOS NUEVOS X 10 UNID | L67: 1.388 | M67: =L67*C67
A68: 4000854 | B68: PACK 10 CAJ. GRIDO CREMOSO AMER. X 10 UN | C68: 0 | E68: 1.388 | F68: =E68*C68 | K68: PALITOS NUEVOS X 10 UNID | L68: 1.388 | M68: =L68*C68
A69: 4000859 | B69: PACK 10 CAJ. PALITO BOMBON GRIDO X 10 U | C69: 0 | E69: 1.388 | F69: =E69*C69 | K69: PALITOS NUEVOS X 10 UNID | L69: 1.388 | M69: =L69*C69
A70: 4000858 | B70: PACK 10 CAJ. GRIDO FRUTAL NARANJA X 10 U | C70: 0 | E70: 1.388 | F70: =E70*C70 | K70: PALITOS NUEVOS X 10 UNID | L70: 1.388 | M70: =L70*C70
A71: 4000855 | B71: PACK 10 CAJ. GRIDO CREMOSO FRUT. X 10 UN | C71: 0 | E71: 1.388 | F71: =E71*C71 | K71: PALITOS NUEVOS X 10 UNID | L71: 1.388 | M71: =L71*C71
A72: 4000742 | B72: PACK X 6 CAJ. ALFAJOR HELADO SHOT - GR | C72: 0 | D72: =SUM(C72:C74) | E72: =VLOOKUP(A72,MATERIALES!A562:D656,4,0) | F72: =E72*C72 | G72: =F72*1.21 | H72: =VLOOKUP(A72,MATERIALES!$A:$E,5,0) | I72: =C72*H72 | J72: 10 | K72: ESCOCES-SHOT-SECRETO | L72: =VLOOKUP(A72,MATERIALES!$A:$D,4,0) | M72: =L72*C72
A73: 4000147 | B73: PACK 6 CAJAS BOMBON ESCOCES X8 - GRIDO | C73: 60 | E73: =VLOOKUP(A73,MATERIALES!A563:D657,4,0) | F73: =E73*C73 | G73: =F73*1.21 | H73: =VLOOKUP(A73,MATERIALES!$A:$E,5,0) | I73: =C73*H73 | K73: ESCOCES-SHOT-SECRETO | L73: =VLOOKUP(A73,MATERIALES!$A:$D,4,0) | M73: =L73*C73
A74: 4000823 | B74: PACK 6 CAJ. ALFAJOR SECRETO COOKIES GR | C74: 27 | E74: 0.92 | F74: =E74*C74 | K74: ESCOCES-SHOT-SECRETO | L74: 0.77 | M74: =L74*C74
A75: 4000142 | B75: PACK 6 CAJAS CASSATA X 8 GRIDO | C75: 5 | D75: =SUM(C75:C77) | E75: =VLOOKUP(A75,MATERIALES!A564:D658,4,0) | F75: =E75*C75 | G75: =F75*1.21 | H75: =VLOOKUP(A75,MATERIALES!$A:$E,5,0) | I75: =C75*H75 | J75: 10 | K75: PORCION | L75: =VLOOKUP(A75,MATERIALES!$A:$D,4,0) | M75: =L75*C75
A76: 4000143 | B76: PACK 6 CAJAS ALMENDRADO X 8 - GRIDO | C76: 13 | E76: =VLOOKUP(A76,MATERIALES!A565:D659,4,0) | F76: =E76*C76 | G76: =F76*1.21 | H76: =VLOOKUP(A76,MATERIALES!$A:$E,5,0) | I76: =C76*H76 | K76: PORCION | L76: =VLOOKUP(A76,MATERIALES!$A:$D,4,0) | M76: =L76*C76
A77: 4000146 | B77: PACK 6 CAJAS BOMBON SUIZO X8 - GRIDO | C77: 19 | E77: =VLOOKUP(A77,MATERIALES!A566:D660,4,0) | F77: =E77*C77 | G77: =F77*1.21 | H77: =VLOOKUP(A77,MATERIALES!$A:$E,5,0) | I77: =C77*H77 | K77: PORCION | L77: =VLOOKUP(A77,MATERIALES!$A:$D,4,0) | M77: =L77*C77
A78: 4000144 | B78: PACK 4 U. POSTRE CROCANTINO - GRIDO | C78: 20 | D78: =SUM(C78:C82) | E78: =VLOOKUP(A78,MATERIALES!A567:D661,4,0) | F78: =E78*C78 | G78: =F78*1.21 | H78: =VLOOKUP(A78,MATERIALES!$A:$E,5,0) | I78: =C78*H78 | J78: 12 | K78: BARRAS | L78: 0.58 | M78: =L78*C78
A79: 4000145 | B79: PACK 6 CAJAS BOMBON CROCANTE X8 - GRIDO | C79: 60 | E79: =VLOOKUP(A79,MATERIALES!A568:D662,4,0) | F79: =E79*C79 | G79: =F79*1.21 | H79: =VLOOKUP(A79,MATERIALES!$A:$E,5,0) | I79: =C79*H79 | K79: BARRAS | L79: 0.58 | M79: =L79*C79
A80: 4000867 | B80: PACK 6 CAJAS BOMBON FRUTEZZA X 8 - GRIDO | C80: 44 | E80: 0.641 | F80: =E80*C80 | G80: =F80*1.21 | K80: BARRAS | L80: 0.58 | M80: =L80*C80
A81: 4000148 | B81: PACK 6 CAJAS BOMBON VAINILLA SPLIT X 8 | C81: 0 | E81: =VLOOKUP(A81,MATERIALES!A569:D663,4,0) | F81: =E81*C81 | G81: =F81*1.21 | H81: =VLOOKUP(A81,MATERIALES!$A:$E,5,0) | I81: =C81*H81 | K81: BARRAS | L81: 0.58 | M81: =L81*C81
A82: 4000593 | B82: PACK 4 U DELICIA DE CHOCO.Y MANÍ - GRIDO | C82: 0 | E82: =VLOOKUP(A82,MATERIALES!A570:D664,4,0) | F82: =E82*C82 | G82: =F82*1.21 | H82: =VLOOKUP(A82,MATERIALES!$A:$E,5,0) | I82: =C82*H82 | K82: BARRAS | L82: 0.58 | M82: =L82*C82
A83: 6002671 | B83: PACK 12 CAJAS PIZZA FRIZZIO 510 grs. | C83: 0 | D83: =SUM(C83:C100) | E83: =VLOOKUP(A83,MATERIALES!A481:D517,4,0) | F83: =C83*E83 | G83: =F83*1.21 | H83: =VLOOKUP(A83,MATERIALES!$A:$E,5,0) | I83: =C83*H83 | J83: 5 | K83: ALIM.CONGELADOS CAJAS GRANDES | L83: 1.2 | M83: =L83*C83
A84: 6002675 | B84: PACK 12 PIZZAS INTEGRAL FRIZZIO 530 grs. | C84: 0 | E84: =VLOOKUP(A84,MATERIALES!A482:D518,4,0) | F84: =C84*E84 | G84: =F84*1.21 | H84: =VLOOKUP(A84,MATERIALES!$A:$E,5,0) | I84: =C84*H84 | K84: ALIM.CONGELADOS CAJAS GRANDES | L84: 1.2 | M84: =L84*C84 | N84: ALIMENTOS CONGELADOS
A85: 6002678 | B85: PACK 11 PIZZAS DE CEBOLLA FRIZZIO 540 gr | C85: 0 | E85: =VLOOKUP(A85,MATERIALES!A483:D519,4,0) | F85: =C85*E85 | G85: =F85*1.21 | H85: =VLOOKUP(A85,MATERIALES!$A:$E,5,0) | I85: =C85*H85 | K85: ALIM.CONGELADOS CAJAS GRANDES | L85: 1.2 | M85: =L85*C85
A86: 6002679 | B86: PACK 11 PIZZAS DE JAMON FRIZZIO 535 grs. | C86: 0 | E86: =VLOOKUP(A86,MATERIALES!A484:D520,4,0) | F86: =C86*E86 | G86: =F86*1.21 | H86: =VLOOKUP(A86,MATERIALES!$A:$E,5,0) | I86: =C86*H86 | K86: ALIM.CONGELADOS CAJAS GRANDES | L86: 1.2 | M86: =L86*C86
A87: 6002680 | B87: PACK X 8 PIZZA FRIZZIO T. CASERA 665 grs | C87: 0 | E87: =VLOOKUP(A87,MATERIALES!A485:D521,4,0) | F87: =C87*E87 | G87: =F87*1.21 | H87: =VLOOKUP(A87,MATERIALES!$A:$E,5,0) | I87: =C87*H87 | K87: ALIM.CONGELADOS CAJAS GRANDES | L87: 1.2 | M87: =L87*C87
A88: 6002674 | B88: PACK 20 UN. MINI PIZZA FRIZZIO X 180 grs | C88: 0 | E88: =VLOOKUP(A88,MATERIALES!A486:D522,4,0) | F88: =C88*E88 | G88: =F88*1.21 | H88: =VLOOKUP(A88,MATERIALES!$A:$E,5,0) | I88: =C88*H88 | K88: ALIM.CONGELADOS CAJAS GRANDES | L88: 1.2 | M88: =L88*C88
A89: 6002672 | B89: PACK 16 UN. BASTONCITOS FRIZZIO 380 grs | C89: 0 | E89: =VLOOKUP(A89,MATERIALES!A487:D523,4,0) | F89: =C89*E89 | G89: =F89*1.21 | H89: =VLOOKUP(A89,MATERIALES!$A:$E,5,0) | I89: =C89*H89 | K89: ALIM.CONGELADOS CAJAS GRANDES | L89: 1.2 | M89: =L89*C89
A90: 6002673 | B90: PACK 16 PECHUGUITA FRIZZIO 380 grs | C90: 0 | E90: =VLOOKUP(A90,MATERIALES!A488:D524,4,0) | F90: =C90*E90 | G90: =F90*1.21 | H90: =VLOOKUP(A90,MATERIALES!$A:$E,5,0) | I90: =C90*H90 | K90: ALIM.CONGELADOS CAJAS GRANDES | L90: 1.2 | M90: =L90*C90
A91: 6002676 | B91: PACK 72 EMPANADAS DE CARNE DE 70 grs. | C91: 0 | E91: =VLOOKUP(A91,MATERIALES!A489:D525,4,0) | F91: =C91*E91 | G91: =F91*1.21 | H91: =VLOOKUP(A91,MATERIALES!$A:$E,5,0) | I91: =C91*H91 | K91: ALIM.CONGELADOS CAJAS GRANDES | L91: 1.2 | M91: =L91*C91
A92: 6002677 | B92: PACK 72 EMPANADAS DE JyQ DE 70 grs. | C92: 0 | E92: =VLOOKUP(A92,MATERIALES!A490:D526,4,0) | F92: =C92*E92 | G92: =F92*1.21 | H92: =VLOOKUP(A92,MATERIALES!$A:$E,5,0) | I92: =C92*H92 | K92: ALIM.CONGELADOS CAJAS GRANDES | L92: 1.2 | M92: =L92*C92
A93: 6003299 | B93: PACK 72 (18X4) EMPANADA DE CARNE FR x80g | C93: 0 | E93: 0.88 | F93: =C93*E93 | K93: ALIM.CONGELADOS CAJAS GRANDES | L93: 1.2 | M93: =L93*C93
A94: 6003300 | B94: PACK 72 (18X4) EMPANADA DE JyQ FR x80g | C94: 0 | E94: 0.88 | F94: =C94*E94 | K94: ALIM.CONGELADOS CAJAS GRANDES | L94: 1.2 | M94: =L94*C94
A95: 6002706 | B95: FRAMBUESA DOBLE CHOCO 24 UN X 160 GR GIO | C95: 0 | E95: =VLOOKUP(A95,MATERIALES!A491:D527,4,0) | F95: =C95*E95 | G95: =F95*1.21 | H95: =VLOOKUP(A95,MATERIALES!$A:$E,5,0) | I95: =C95*H95 | K95: ALIM.CONGELADOS CAJAS GRANDES | L95: 1.2 | M95: =L95*C95
A96: 6002707 | B96: FRUTILLA BAÑADA C/CHOC 24 UNX 160 GR GI | C96: 0 | E96: =VLOOKUP(A96,MATERIALES!A492:D528,4,0) | F96: =C96*E96 | G96: =F96*1.21 | H96: =VLOOKUP(A96,MATERIALES!$A:$E,5,0) | I96: =C96*H96 | K96: ALIM.CONGELADOS CAJAS GRANDES | L96: 1.2 | M96: =L96*C96
A97: 6003173 | B97: PACK 16 PAPAS FR MCCAIN CRINKLE X 600G | C97: 0 | E97: =VLOOKUP(A97,MATERIALES!A493:D529,4,0) | F97: =C97*E97 | G97: =F97*1.21 | H97: =VLOOKUP(A97,MATERIALES!$A:$E,5,0) | I97: =C97*H97 | K97: ALIM.CONGELADOS CAJAS GRANDES | L97: 1.2 | M97: =L97*C97
A98: 6003172 | B98: PACK 16 PAPAS FR MCCAIN NOISSETE X 600G | C98: 0 | E98: =VLOOKUP(A98,MATERIALES!A494:D530,4,0) | F98: =C98*E98 | G98: =F98*1.21 | H98: =VLOOKUP(A98,MATERIALES!$A:$E,5,0) | I98: =C98*H98 | K98: ALIM.CONGELADOS CAJAS GRANDES | L98: 1.2 | M98: =L98*C98
A99: 6003171 | B99: PACK 16 PAPAS FR MCCAIN CORT TRAD X 700G | C99: 0 | E99: =VLOOKUP(A99,MATERIALES!A495:D531,4,0) | F99: =C99*E99 | G99: =F99*1.21 | H99: =VLOOKUP(A99,MATERIALES!$A:$E,5,0) | I99: =C99*H99 | K99: ALIM.CONGELADOS CAJAS GRANDES | L99: 1.2 | M99: =L99*C99
A100: 6002842 | B100: MEDIALUNA X 144 UN FUDY | C100: 0 | E100: =VLOOKUP(A100,MATERIALES!A496:D532,4,0) | F100: =C100*E100 | G100: =F100*1.21 | H100: =VLOOKUP(A100,MATERIALES!$A:$E,5,0) | I100: =C100*H100 | K100: ALIM.CONGELADOS CAJAS GRANDES | L100: 1.2 | M100: =L100*C100
A101: 6002435 | B101: BOCADITOS FRUTILLAS DOBLE CHOC. 24 UN | C101: 0 | D101: =SUM(C101:C126) | E101: =VLOOKUP(A101,MATERIALES!A497:D533,4,0) | F101: =C101*E101 | G101: =F101*1.21 | H101: =VLOOKUP(A101,MATERIALES!$A:$E,5,0) | I101: =C101*H101 | J101: 5 | K101: ALIM.CONGELADOS CAJAS CHICAS | L101: 0.6 | M101: =L101*C101
A102: 6002434 | B102: BOCADITOS FRAMBUESAS DOBLE CHOC. 24 UN | C102: 0 | E102: =VLOOKUP(A102,MATERIALES!A498:D534,4,0) | F102: =C102*E102 | G102: =F102*1.21 | H102: =VLOOKUP(A102,MATERIALES!$A:$E,5,0) | I102: =C102*H102 | K102: ALIM.CONGELADOS CAJAS CHICAS | L102: 0.6 | M102: =L102*C102
...

Sheet Hoja1
A1: B000302792 | B1: 4000065 | C1: 2 | D1: 0 | E1: 1000 | F1: 1004 | G1: Pedido WEB nro.1411479
A2: B000302792 | B2: 6002678 | C2: 1 | D2: 0 | E2: 1000 | F2: 1004 | G2: Pedido WEB nro.1411479
A3: B000302792 | B3: 6002672 | C3: 1 | D3: 0 | E3: 1000 | F3: 1004 | G3: Pedido WEB nro.1411479
A4: B000302792 | B4: 6002675 | C4: 1 | D4: 0 | E4: 1000 | F4: 1004 | G4: Pedido WEB nro.1411479
A5: B000302792 | B5: 6002712 | C5: 1 | D5: 0 | E5: 1000 | F5: 1004 | G5: Pedido WEB nro.1411479
A6: B000302792 | B6: 6003150 | C6: 1 | D6: 0 | E6: 1000 | F6: 1004 | G6: Pedido WEB nro.1411479
A7: B000302792 | B7: 4000670 | C7: 3 | D7: 0 | E7: 1000 | F7: 1004 | G7: Pedido WEB nro.1411479
A8: B000302792 | B8: 4000341 | C8: 2 | D8: 0 | E8: 1000 | F8: 1004 | G8: Pedido WEB nro.1411479
A9: B000302792 | B9: 4000152 | C9: 2 | D9: 0 | E9: 1000 | F9: 1004 | G9: Pedido WEB nro.1411479
A10: B000302792 | B10: 4000162 | C10: 2 | D10: 0 | E10: 1000 | F10: 1004 | G10: Pedido WEB nro.1411479
A11: B000302792 | B11: 4000160 | C11: 5 | D11: 0 | E11: 1000 | F11: 1004 | G11: Pedido WEB nro.1411479
A12: B000302792 | B12: 4000153 | C12: 3 | D12: 0 | E12: 1000 | F12: 1004 | G12: Pedido WEB nro.1411479
... A73: B000302792 | B73: 6002671 | C73: 2 | D73: 0 | E73: 1000 | F73: 1004 | G73: Pedido WEB nro.1411479

Sheet franquicias
A1: Klappen | B1: Titular FACTURABLE
A2: 100271-1 | B2: CABRERA, GUSTAVO RAFAEL
A3: 100696-3 | B3: PROGRESO J&T S.A.
A4: 100375 | B4: LIZONDO, MARIA GRACIELA
A5: 100144 | B5: BOSCO, HECTOR JAVIER
A6: 100143 | B6: SALVADOR, FERRER ALVAREZ
A7: 100697-1 | B7: OCTI S.R.L.
A8: 101051-1 | B8: CORDOBA HELADERIAS S.A.S.
A9: 100279 | B9: ROSSI, LUCIANO BENJAMIN
A10: 100621 | B10: LUCCRA S.A.
A11: 100621-2 | B11: LUCCRA S.A.
A12: 101191 | B12: VILLALBA PAULA MARIELA
A13: 101384 | B13: HERNANDEZ CASASOLA MARIA EUGEN
A14: 100147 | B14: LONDERO, MAURO SEBASTIAN
A15: 100684 | B15: RETIA S.R.L
A16: 100419 | B16: ESCALANTE PAZ, MARIA FERNANDA
A17: 100247-1 | B17: CHAILE HERNAN NICOLAS
A18: 100964 | B18: ODETTI, LUCIANA LAURA
A19: 100413 | B19: PALAT, KARINA MARIEL
A20: 101092 | B20: WAIGEL, JEREMIAS NAHUEL
A21: 100732-1 | B21: MANOLETE Y MANOLETA S.R.L.
A22: 100731 | B22: LA TOTO S.R.L.
A23: 101111 | B23: LOPEZ LORENA RAQUEL
A24: 100003 | B24: RODRIGUEZ, JUAN DOMINGO
A25: 101051-2 | B25: CORDOBA HELADERIAS S.A.S.
A26: 100697-4 | B26: OCTI S.R.L.
A27: 100896-1 | B27: HELADOS SAN VICENTE S.R.L.
A28: 100656-3 | B28: GENKO S.A.
A29: 100510 | B29: GARCIA, VERONICA EVANGELINA
A30: 100213 | B30: ZACHARSKI, JORGE MATIAS
A31: 100288 | B31: HEREDIA D´AGOSTINO, MATIAS
A32: 100732 | B32: MANOLETE Y MANOLETA S.R.L.
A33: 100696-4 | B33: PROGRESO J&T S.A.
A34: 100634 | B34: USHPA S.R.L.
A35: 100701-1 | B35: GRUPO ABG S.R.L.
A36: 101292 | B36: GOTAMA S.A.S.
A37: 100472 | B37: RODRIGUEZ VAGLIERA, LORENA VAN
A38: 100031 | B38: PEREYRA, LUIS ANGEL
A39: 101204 | B39: MERCADO ADRIAN ENRIQUE
A40: 100102 | B40: ZAMPETTI, MARCELO RAFAEL
A41: 101034 | B41: SENA, MILENA DEL VALLE
A42: 100271 | B42: CABRERA, GUSTAVO RAFAEL
A43: 101097 | B43: GOMEZ, ROMINA DEL VALLE
A44: 101414 | B44: CASTRO FABRIZIO OMAR
A45: 100201 | B45: OLIVER, CARLOS MATIAS
A46: 100535-1 | B46: PEDERNERA MARIA LAURA
A47: 100598-2 | B47: MODOS SA
A48: 101008 | B48: ALIMIA S.A.S.
A49: 101375 | B49: ICE WORLD S.A.S.
A50: 101132 | B50: ICECOR S.A.S
A51: 101263 | B51: MORENO NICOLAS ARIEL
A52: 100777 | B52: SOLBER S.R.L.
A53: 101302 | B53: MABAIG S.A.S.
A54: 101340-1 | B54: BLEMA S.A.S.
A55: 101272 | B55: SUPERFRIO S.A.S.
A56: 100029 | B56: BERNAY, HORACIO DANIEL
A57: 101103-1 | B57: UNITED GROUP S.A.
A58: 100247 | B58: CHAILE HERNAN NICOLAS
A59: 100351 | B59: FRAGUEIRO, GUILLERMO JORGE
A60: 101315 | B60: PARAJE AGUSTIN FEDERICO
A61: 100428 | B61: CESANO, VERONICA SILVIA
A62: 101210 | B62: PROYECTOS DORADOS S.A.S.
A63: 100393 | B63: MEDINA, MIRIAM DEL VALLE
A64: 100398-1 | B64: BORIS LILIANA MARGARITA DEL VA
A65: 100069 | B65: DE SIMONE PABLO
A66: 100547 | B66: CHENA, ANA CAROLINA
A67: 101037 | B67: SANCHEZ, CAROLINA
A68: 100777-2 | B68: SOLBER S.R.L.
A69: 101101 | B69: ACUÑA SEGURA MARINA CELESTE
A70: 100001 | B70: WERLEN, HECTOR JUAN
A71: 100420 | B71: FLORES, ELSA SANDRA
A72: 100730 | B72: HIPOLITITO S.R.L.
A73: 100653 | B73: NUSS GRACIELA BEATRIZ Y PAZ MI
A74: 101340 | B74: BLEMA S.A.S.
A75: 100251 | B75: BARRIONUEVO, LUCAS DAMIAN
A76: 100291 | B76: NACHTIGAL, CARLOS GUSTAVO M
A77: 100069-1 | B77: DE SIMONE PABLO
A78: 101205 | B78: MIL SABORES S.A.S
A79: 101338 | B79: BOJANICH EMILIANO ESTEBAN
A80: 101060 | B80: ALTAMIRANO BONGIORNO, CARLOS S
A81: 100391 | B81: SALINA, PATRICIA ALEJANDRA
A82: 100420-1 | B82: FLORES, ELSA SANDRA
A83: 101208 | B83: ALBERTINI ALICIA LEONOR
A84: 101236 | B84: PERALTA FAVIO DARIO
A85: 100604-3 | B85: PRETER SA
A86: 100604 | B86: PRETER SA
A87: 101206 | B87: PEÑA PEREA NADIA YAEL
A88: 100725 | B88: ROECHE S.R.L.
A89: 101127 | B89: CANO ANALIA DE LOS ANGELES
A90: 100201-1 | B90: OLIVER, CARLOS MATIAS
A91: 101271 | B91: RED DE CONGELADOS S.A.S.
A92: 100604-2 | B92: PRETER SA
A93: 101185-2 | B93: MATOCA S.A.S.
A94: 100391-1 | B94: SALINA, PATRICIA ALEJANDRA
A95: 101424 | B95: CORNEJO NATALIA SOLEDAD
A96: 100568 | B96: PINO, FLAVIA ANAHI
A97: 100714 | B97: SIVA S.A.
A98: 100592-2 | B98: ADN S.R.L.
A99: 101051-4 | B99: CORDOBA HELADERIAS S.A.S.
A100: 100081-3 | B100: JAWAHAR, ANGEL MARCIAL
...

Sheet MATERIALES
A1: Codigo | B1: Deposito | C1: Descripcion | D1: Cubicaje | E1: Peso | F1: impuestoIva | G1: precio
A2: 4000050 | B2: 1000;1004 | C2: SUPER GRIDITO 7,800 KG GRIDO | D2: 0.8 | E2: 7.8 | F2: 0 | G2: 4998.53 | H2: 100 | I2: 110 | J2: =H2*D2/I2
A3: 4000044 | B3: 1000;1004 | C3: VAINILLA 7,800 KG GRIDO | D3: 0.8 | E3: 7.8 | F3: 0 | G3: 4998.53 | H3: 100 | I3: 110 | J3: =H3*D3/I3
A4: 4000036 | B4: 1000;1004 | C4: LIMON AL AGUA 7,800 KG GRIDO | D4: 0.8 | E4: 7.8 | F4: 0 | G4: 2706.22 | H4: 100 | I4: 110 | J4: =H4*D4/I4
A5: 4000042 | B5: 1000;1004 | C5: FRUTILLA A LA CREMA 7,800KG GRIDO | D5: 0.8 | E5: 7.8 | F5: 0 | G5: 4998.53 | H5: 100 | I5: 110 | J5: =H5*D5/I5
A6: 4000056 | B6: 1000;1004 | C6: KINOTOS AL WHISKY 7,800 KG GRIDO | D6: 0.8 | E6: 7.8 | F6: 0 | G6: 5461.98 | H6: 100 | I6: 110 | J6: =H6*D6/I6
A7: 4000043 | B7: 1000;1004 | C7: CHOCOLATE 7,800 KG GRIDO | D7: 0.8 | E7: 7.8 | F7: 0 | G7: 4998.53 | H7: 100 | I7: 110 | J7: =H7*D7/I7
A8: 4000061 | B8: 1000;1004 | C8: CHOCOLATE MANI CRUNCH 7,800 KG GRIDO | D8: 0.8 | E8: 7.8 | F8: 0 | G8: 5461.98 | H8: 100 | I8: 110 | J8: =H8*D8/I8
A9: 4000068 | B9: 1000;1004 | C9: DULCE LECHE C/NUEZ 7,800 KG GRIDO | D9: 0.8 | E9: 7.8 | F9: 0 | G9: 6079.84 | H9: 100 | I9: 110 | J9: =H9*D9/I9
A10: 4000045 | B10: 1000;1004 | C10: CREMA AMERICANA 7,800 KG GRIDO | D10: 0.8 | E10: 7.8 | F10: 0 | G10: 4998.53 | H10: 100 | I10: 110 | J10: =H10*D10/I10
A11: 4000047 | B11: 1000;1004 | C11: FLAN 7,800 KG GRIDO | D11: 0.8 | E11: 7.8 | F11: 0 | G11: 4998.53 | H11: 100 | I11: 110 | J11: =H11*D11/I11
A12: 4000048 | B12: 1000;1004 | C12: BANANA C/DULC LECHE 7,800 KG GRIDO | D12: 0.8 | E12: 7.8 | F12: 0 | G12: 4998.53 | H12: 100 | I12: 110 | J12: =H12*D12/I12
A13: 4000049 | B13: 1000;1004 | C13: MENTA GRANIZADA 7,800 KG GRIDO | D13: 0.8 | E13: 7.8 | F13: 0 | G13: 4998.53 | H13: 100 | I13: 110 | J13: =H13*D13/I13
... A80: 6002671 | B80: 1000;1004 | C80: PACK 12 CAJAS PIZZA FRIZZIO 510 grs. | D80: 0.76363636 | E80: 0.51 | F80: 0 | G80: 8496.21 | H80: 100 | I80: 110 | J80: =H80*D80/I80
A81: 6002672 | B81: 1000;1004 | C81: PACK 16 UN. BASTONCITOS FRIZZIO 380 grs | D81: 0.94727273 | E81: 6.08 | F81: 0 | G81: 10653.3 | H81: 100 | I81: 110 | J81: =H81*D81/I81 | K81: =J81*12
A82: 6002673 | B82: 1000;1004 | C82: PACK 16 PECHUGUITA FRIZZIO 380 grs | D82: 1.0818182 | E82: 6.08 | F82: 0 | G82: 9611.78 | H82: 100 | I82: 110 | J82: =H82*D82/I82
A83: 6002674 | B83: 1000;1004 | C83: PACK 20 UN. MINI PIZZA FRIZZIO X 180 grs | D83: 0.94727273 | E83: 3.6 | F83: 0 | G83: 6877.24 | H83: 100 | I83: 110 | J83: =H83*D83/I83
A84: 6002675 | B84: 1000;1004 | C84: PACK 12 PIZZAS INTEGRAL FRIZZIO 530 grs. | D84: 1.2627273 | E84: 6.36 | F84: 0 | G84: 8742 | H84: 100 | I84: 110 | J84: =H84*D84/I84
A85: 6002676 | B85: 1000;1004 | C85: PACK 72 EMPANADAS DE CARNE DE 70 grs. | D85: 1.2627273 | E85: 5.04 | F85: 0 | G85: 7805.27 | H85: 100 | I85: 110 | J85: =H85*D85/I85
A86: 6002677 | B86: 1000;1004 | C86: PACK 72 EMPANADAS DE JyQ DE 70 grs. | D86: 1.0327273 | E86: 5.04 | F86: 0 | G86: 8313.5 | H86: 100 | I86: 110 | J86: =H86*D86/I86
A87: 6002678 | B87: 1000;1004 | C87: PACK 11 PIZZAS DE CEBOLLA FRIZZIO 540 gr | D87: 1.2627273 | E87: 5.94 | F87: 0 | G87: 7724.86 | H87: 100 | I87: 110 | J87: =H87*D87/I87
A88: 6002679 | B88: 1000;1004 | C88: PACK 11 PIZZAS DE JAMON FRIZZIO 535 grs. | D88: 1.2627273 | E88: 5.88 | F88: 0 | G88: 8619 | H88: 100 | I88: 110 | J88: =H88*D88/I88
A89: 6002680 | B89: 1000;1004 | C89: PACK X 8 PIZZA FRIZZIO T. CASERA 665 grs | D89: 1.2627273 | E89: 5.32 | F89: 0 | G89: 8311.9 | H89: 100 | I89: 110 | J89: =H89*D89/I89
A90: 6002681 | B90: 1000;1004 | C90: CAPUCHON SUNDAE GO SHOT X 70 UN | D90: 1.0818182 | E90: 0.01 | F90: 0 | G90: 9268.42 | H90: 100 | I90: 110 | J90: =H90*D90/I90
A91: 6002682 | B91: 1000;1004 | C91: PACK X 6 POSTRE CREMOSO - TIRAMISU | D91: 0.99909091 | E91: 4.5 | F91: 0 | G91: 8449.29 | H91: 100 | I91: 110 | J91: =H91*D91/I91
A92: 6002683 | B92: 1000;1004 | C92: PACK X 6 POSTRE CREMOSO - LEMON PIE | D92: 0.99909091 | E92: 4.5 | F92: 0 | G92: 8449.29 | H92: 100 | I92: 110 | J92: =H92*D92/I92
A93: 6002684 | B93: 1000;1004 | C93: PACK X 6 POSTRE CREMOSO- CREM DE CHOCOL. | D93: 0.99909091 | E93: 4.5 | F93: 0 | G93: 8449.29 | H93: 100 | I93: 110 | J93: =H93*D93/I93
... A128: 6002844 | B128: 1000;1004 | C128: MUFFIN CHOCOLATE X 10 UN FUDY | D128: 1.8181818 | E128: 1.35 | F128: 0 | G128: 3074.59 | H128: 100 | I128: 110 | J128: =H128*D128/I128
A129: 6002845 | B129: 1000;1004 | C129: PACK 18 VIANDA POLLO AL DISCO C/VEG | D129: 0 | F129: 0 | G129: 10333 | H129: 100 | I129: 110 | J129: =H129*D129/I129
A130: 6002846 | B130: 1000;1004 | C130: VIANDA X 18 MILANESAS CON PURE | D130: 1.2981818 | E130: 9.6 | F130: 0 | G130: 10333 | H130: 100 | I130: 110 | J130: =H130*D130/I130
A131: 6002848 | B131: 1000;1004 | C131: PACK 24 VIANDAS PASTEL DE PAPAS | D131: 1.2981818 | E131: 9.6 | F131: 0 | G131: 14555.74 | H131: 100 | I131: 110 | J131: =H131*D131/I131
A132: 6002849 | B132: 1000;1004 | C132: PACK 24 VIANDAS CANELONES DE CARNE | D132: 1.5090909 | E132: 10.8 | F132: 0 | G132: 14555.74 | H132: 100 | I132: 110 | J132: =H132*D132/I132
A133: 6002850 | B133: 1000;1004 | C133: PACK 24 VIAN. LASAG DE C. C/ ESPINACA NR | D133: 1.2981818 | E133: 10.8 | F133: 0 | G133: 13166.17 | H133: 100 | I133: 110 | J133: =H133*D133/I133
A134: 6002851 | B134: 1000;1004 | C134: PACK 24 VIANDA LASAGNA BOLOG. CON JYQ NR | D134: 1.2981818 | E134: 10.8 | F134: 0 | G134: 13166.17 | H134: 100 | I134: 110 | J134: =H134*D134/I134
A135: 6002854 | B135: 1000;1004 | C135: BUDIN LIMON C/ AMAPOLA X 20 UN FUDY | D135: 1.8181818 | E135: 1.8 | F135: 0 | G135: 4853 | H135: 100 | I135: 110 | J135: =H135*D135/I135
A136: 6002858 | B136: 1000;1004 | C136: PACK X 18 PAPAS MACCAI NOSETTE X 500 GRS | D136: 1.01 | E136: 9 | F136: 0 | G136: 7861.44 | H136: 100 | I136: 110 | J136: =H136*D136/I136
A137: 6002804 | B137: 1000;1004 | C137: PACK 12 PAPAS SMILE MCAIN 600 GR | D137: 1.01 | E137: 7.2 | F137: 0 | G137: 10424.3 | H137: 100 | I137: 110 | J137: =H137*D137/I137
A138: COMBO MIX PIZZA 50% | B138: 1000;1004 | C138: COMBO MIX PIZZA 50% | D138: 6.7618182 | E138: 27.61 | F138: 0 | G138: 343310.36 | H138: 100 | I138: 110 | J138: =H138*D138/I138
A139: COMBO PIZZA 100% | B139: 1000;1004 | C139: COMBO MIX PIZZA 100% | D139: 6.7618182 | E139: 27.61 | F139: 0 | G139: 692726.61 | H139: 100 | I139: 110 | J139: =H139*D139/I139
A140: 4000440 | B140: 1000;1004 | C140: PALITO AGUA SABOR FRUTILLA VB C. x 80UN | D140: 0.84181818 | E140: 4.4 | F140: 0 | G140: 2472.21 | H140: 100 | I140: 110 | J140: =H140*D140/I140
A141: 4000441 | B141: 1000;1004 | C141: PALITO AGUA SABOR NARANJA VB CAJA x 80UN | D141: 0.84181818 | E141: 4.4 | F141: 0 | G141: 2472.21 | H141: 100 | I141: 110 | J141: =H141*D141/I141
A142: 4000438 | B142: 1000;1004 | C142: PALITO CREMA SABOR FRUTILLA VB C. x 80UN | D142: 0.84181818 | E142: 3.2 | F142: 0 | G142: 3616.48 | H142: 100 | I142: 110 | J142: =H142*D142/I142
A143: 4000442 | B143: 1000;1004 | C143: PALITO AGUA SABOR LIMON VB CAJA x 80 UN | D143: 0.84181818 | E143: 4.4 | F143: 0 | G143: 2472.21 | H143: 100 | I143: 110 | J143: =H143*D143/I143
A144: 4000437 | B144: 1000;1004 | C144: PALITO CREMA AMERICANA VB CAJA x 80 UN | D144: 0.84181818 | E144: 3.2 | F144: 0 | G144: 3616.48 | H144: 100 | I144: 110 | J144: =H144*D144/I144
A145: 4000758 | B145: 1000;1004 | C145: CREMA DEL CIELO 7,800 KG GRIDO | D145: 0.8 | E145: 7.8 | F145: 0 | G145: 4998.53 | H145: 100 | I145: 110 | J145: =H145*D145/I145
A146: 4000439 | B146: 1000;1004 | C146: PALITO BOMBON VB CAJA x 80 UN | D146: 0.84181818 | E146: 4.08 | F146: 0 | G146: 4698.12 | H146: 100 | I146: 110 | J146: =H146*D146/I146
A147: 6000001 | B147: 2000;2000 | C147: FLY BANNER FRIZZIO 2.60 x 0.80 mts | D147: 0.18181818 | E147: 1.15 | F147: 0 | G147: 14885.91 | H147: 100 | I147: 110 | J147: =H147*D147/I147
A148: 6000087 | B148: 2000;2000 | C148: CABEZAL DE POLIPROPILENOPARA MOPA | D148: 0.18181818 | E148: 0.85 | F148: 0 | G148: 601.37 | H148: 100 | I148: 110 | J148: =H148*D148/I148
A149: 6000000 | B149: 2000;2000 | C149: FLY BANNER GRIDO 2.60 x 0.80 mts | D149: 0.18181818 | E149: 1.15 | F149: 0 | G149: 14885.91 | H149: 100 | I149: 110 | J149: =H149*D149/I149
A150: 6000063 | B150: 2000;2000 | C150: BAÑO CHOCO REPOSTERÍA SEMI AMARGO X 10 | D150: 1.4204545 | E150: 10.64 | F150: 0 | G150: 11985.12 | H150: 100 | I150: 110 | J150: =H150*D150/I150
A151: 6000199 | B151: 2000;2000 | C151: DESINFECTANTE APTO ALIMENTACION X 5 LTS | D151: 0.75757273 | E151: 5.21 | F151: 0 | G151: 2103.92 | H151: 100 | I151: 110 | J151: =H151*D151/I151
... A451: 6000156 | B451: 2000;2000 | C451: CONSERVADORA MOD. FAM I 355 FRIZZIO | D451: 90.909091 | E451: 35 | F451: 0 | G451: 200684.03 | H451: 100 | I451: 110 | J451: =H451*D451/I451
A452: 6000158 | B452: 2000;2000 | C452: CONSERVADORA MOD. FAM I 555 PLOT FRIZZIO | D452: 0 | F452: 0 | G452: 246545.11 | H452: 100 | I452: 110 | J452: =H452*D452/I452
A453: 7100104 | B453: 2000;2000 | C453: KIT PROMOCIONAL KILO DE SONRISAS 2023 | D453: 0.00090909091 | E453: 0.5 | F453: 0 | G453: 1 | H453: 100 | I453: 110 | J453: =H453*D453/I453
A454: 6002958 | B454: 2000;2000 | C454: KIT PROMOCIONAL RASTI 2° EDICIÓN (MONST) | D454: 3.0272727 | E454: 1.5 | F454: 0 | G454: 2819.84 | H454: 100 | I454: 110 | J454: =H454*D454/I454
A455: 6002918 | B455: 2000;2000 | C455: CUCHARA RASTI 2° EDICIÓN + KIT X 60 UN | D455: 3.0272727 | E455: 1.5 | F455: 0 | G455: 14086.21 | H455: 100 | I455: 110 | J455: =H455*D455/I455
A456: 6002629 | B456: 2000;2000 | C456: SORBETE FLEXIBLE 100 % PAPEL X 100UN | D456: 3.7872727 | E456: 1 | F456: 0 | G456: 2316.09 | H456: 100 | I456: 110 | J456: =H456*D456/I456
A457: 6002943 | B457: 2000;2000 | C457: SILLA RIO BLANCA X UN | D457: 3.7818182 | E457: 1 | F457: 0 | G457: 15020.79 | H457: 100 | I457: 110 | J457: =H457*D457/I457
A458: 6002929 | B458: 2000;2000 | C458: KIT INGRESO COLABOADORES DE FRANQUICIAS | D458: 0.018181818 | E458: 0.02 | F458: 0 | G458: 4206.6 | H458: 100 | I458: 110 | J458: =H458*D458/I458
A459: 6002946 | B459: 2000;2000 | C459: MATERIAL PROMOCIONAL COMERCIAL SIN COSTO | D459: 0.018181818 | E459: 0.2 | F459: 0 | G459: 0.01 | H459: 100 | I459: 110 | J459: =H459*D459/I459
A460: 6002960 | B460: 2000;2000 | C460: PACK CELEBRACION | D460: 3.0272727 | E460: 1.2 | F460: 0 | G460: 12912.21 | H460: 100 | I460: 110 | J460: =H460*D460/I460
A461: 4000154 | D461: 0.51 | H461: 100 | I461: 110
A462: 4000339 | D462: 0.556 | H462: 100 | I462: 110
A463: 4000827 | C463: CHOCO BLANCO OREO 7,800 KG GRIDO | D463: 0.8 | E463: 7.8
A464: 4000817 | C464: MIX PAT/BSAS 23-24 | D464: 100 | E464: 615
A465: 6002855 | C465: PACK 4 CAJAS POSTRE VEGANO CHOCOLATE -GR | E465: 1.92
A466: 6002856 | C466: PACK 4 CAJAS POSTRE VEGANO VANILLA - GR | E466: 1.92
A467: 6002857 | C467: PACK 4 CAJAS POSTRE VEGANO MANI - GR | E467: 1.92
A468: 6002819 | C468: PACK X 6 POSTRE CREMOSO- CREM. DE FRUTAS | E468: 4.5
A469: 4000835 | C469: PACK X 6 TORTA COOKIES AND CREAM GR | D469: 1.2 | E469: 6.27
A471: 4000843 | C471: PACK X 6 TORTA COOKIES MOUSSE GR | D471: 1.2 | E471: 6.27
C472: ALFAJOR HELADO SHOT - GR MONOPRODUCTO | D472: 0.61728395
C473: BOMBON ESCOCES X8 - GRIDO MONOPRODUCTO | D473: 0.71428571
C474: CASSATA X 8 GRIDO MONOPRODUCTO | D474: 0.6993007
C475: ALMENDRADO X 8 - GRIDO MONOPRODUCTO | D475: 0.6993007
C476: BOMBON SUIZO X8 - GRIDO MONOPRODUCTO | D476: 0.6993007
C477: CROCANTINO - GRIDO MONOPRODUCTO | D477: 0.47619048
C478: BOMBON CROCANTE X8 - GRIDO MONOPRODUCTO | D478: 0.5952381
C479: BOMBON VAINILLA SPLIT X 8 MONOPRODUCTO | D479: 0.5952381
C480: DELICIA DE CHOCO.Y MANÍ - GRIDO MONOPRODUCTO | D480: 0.47619048
A481: 6002671 | C481: PACK 12 CAJAS PIZZA FRIZZIO 510 grs. | D481: 0.84
A482: 6002675 | C482: PACK 12 PIZZAS INTEGRAL FRIZZIO 530 grs. | D482: 0.84
A483: 6002678 | C483: PACK 11 PIZZAS DE CEBOLLA FRIZZIO 540 gr | D483: 0.84
A484: 6002679 | C484: PACK 11 PIZZAS DE JAMON FRIZZIO 535 grs. | D484: 0.84
A485: 6002680 | C485: PACK X 8 PIZZA FRIZZIO T. CASERA 665 grs | D485: 0.84
A486: 6002674 | C486: PACK 20 UN. MINI PIZZA FRIZZIO X 180 grs | D486: 0.96
A487: 6002672 | C487: PACK 16 UN. BASTONCITOS FRIZZIO 380 grs | D487: 0.96
A488: 6002673 | C488: PACK 16 PECHUGUITA FRIZZIO 380 grs | D488: 0.96
A489: 6002676 | C489: PACK 72 EMPANADAS DE CARNE DE 70 grs. | D489: 0.88
A490: 6002677 | C490: PACK 72 EMPANADAS DE JyQ DE 70 grs. | D490: 0.88
A491: 6002706 | C491: FRAMBUESA DOBLE CHOCO 24 UN X 160 GR GIO | D491: 0.8
A492: 6002707 | C492: FRUTILLA BAÑADA C/CHOC 24 UNX 160 GR GI | D492: 0.8
... A517: 6003050 | C517: PACK 6 CAJAS PIZZA FRIZZIO 510 grs | D517: 0.92
A518: 4000062 | B518: PB | C518: ANANA A LA CREMA 7,800 KG GRIDO | D518: 0.85
A519: 4000048 | B519: PB | C519: BANANA C/DULC LECHE 7,800 KG GRIDO | D519: 0.85
A520: 4000608 | B520: PB | C520: CANDY 7,800 KG GRIDO | D520: 0.85
A521: 4000193 | B521: PB | C521: CAPPUCCINO GRANIZADO 7,800 KG GRIDO | D521: 0.85
A522: 4000070 | B522: PB | C522: CEREZA 7,800 KG - GRIDO | D522: 0.85
A523: 4000827 | B523: PB | C523: CHOCO BLANCO OREO 7,800 KG GRIDO | D523: 0.85
A524: 4000043 | B524: PB | C524: CHOCOLATE 7,800 KG GRIDO | D524: 0.85
...

Sheet LISTA Z1
A1: 4000036 | B1: LIMON AL AGUA 7,800 KG GRIDO | C1: 10232.17
A2: 4000038 | B2: MARACUYA AL AGUA 7,800 KG GRIDO | C2: 10232.17
A3: 4000039 | B3: NARANJA AL AGUA 12 7,800 KG GRIDO | C3: 10232.17
A4: 4000040 | B4: GRANIZADO 7,800 KG GRIDO | C4: 19297.96
A5: 4000041 | B5: DULCE DE LECHE 7,800 KG GRIDO | C5: 19297.96
A6: 4000042 | B6: FRUTILLA A LA CREMA 7,800KG GRIDO | C6: 19297.96
A7: 4000043 | B7: CHOCOLATE 7,800 KG GRIDO | C7: 19297.96
A8: 4000044 | B8: VAINILLA 7,800 KG GRIDO | C8: 19297.96
A9: 4000045 | B9: CREMA AMERICANA 7,800 KG GRIDO | C9: 19297.96
A10: 4000046 | B10: DULCE LECHE GRANIZADO 7,800 KG GRIDO | C10: 19297.96
A11: 4000047 | B11: FLAN 7,800 KG GRIDO | C11: 19297.96
A12: 4000048 | B12: BANANA C/DULC LECHE 7,800 KG GRIDO | C12: 19297.96
... A108: 6002857 | B108: PACK 4 CAJAS POSTRE VEGANO MANI - GR | C108: 22786.28

Sheet multiplos 
A1: FAMILIAS | B1: PRODUCTOS | C1: BASES | D1: PORCENTAJE BASE
A2: GRANEL | B2: TODOS | C2: 25 | D2: 20
A3: POTES 3L | B3: TODOS | C3: 15 | D3: 16.35
A4: TORTAS | B4: TODOS | C4: 10 | D4: 12
A5: TENTACIÓN | B5: TODOS | C5: 15 | D5: 7.5818182
A6: PALITOS | B6: TODOS | C6: 15 | D6: 12.3
A7: ESCOCES-SHOT | B7: ESCOCES-SHOT | C7: 10 | D7: 7.7
A8: PORCIÓN | B8: ALMENDRADO- SUIZO- CASATTA | C8: 10 | D8: 7.7
A9: BARRAS | B9: DELICIA-CROCANTINO-VAINILLA SPLIT-CROCANTE | C9: 12 | D9: 6.9927273
A10: ALIMENTOS CONGELADOS | B10: TODOS | C10: 9 | D10: 14
